rmsdk/RMSDK.py
rmsdk/__init__.py
rmsdk/auth.py
rmsdk/exceptions.py
rmsdk/loyalty.py
rmsdk/merchant.py
rmsdk/model.py
rmsdk/payment.py
rmsdk/request.py
rmsdk/store.py
rmsdk/user.py
rmsdk/utils.py
rmsdk/voucher.py
rmsdk-1.0.1.dist-info/LICENSE
rmsdk-1.0.1.dist-info/METADATA
rmsdk-1.0.1.dist-info/WHEEL
rmsdk-1.0.1.dist-info/top_level.txt
rmsdk-1.0.1.dist-info/RECORD
