Metadata-Version: 2.1
Name: rmsdk
Version: 1.0.1
Summary: A Python wrapper around the Revenue Monster API
Home-page: https://github.com/RevenueMonster/RM-API-SDK-Python
Author: Rex Low
Author-email: rex@revenuemonster.my
Maintainer: Rex Low
License: MIT
Keywords: RevenueMonster SDK API
Platform: UNKNOWN
Classifier: Environment :: Console
Classifier: Intended Audience :: Developers
Classifier: License :: OSI Approved :: MIT License
Classifier: Operating System :: OS Independent
Classifier: Programming Language :: Python :: 3
Requires-Dist: pycryptodome
Requires-Dist: requests
